<form>
  <label>CPU Performance</label>
  <fieldset autorun="true" submitButton="false">
  <input type="time" searchWhenChanged="true">
      <label>Select time range</label>
      <default>
        <earliest>-24h@h</earliest>
        <latest>now</latest>
      </default>
    </input>
    <input type="dropdown" token="node" searchWhenChanged="true">
      <label>Select a Node</label>
      
      <default>*</default>
      
     <!-- Define the default value -->      
      <choice value="*">All</choice>
      
     <!-- Define the choices with a populating search -->
      <populatingSearch fieldForValue="HOSTADDR" fieldForLabel="node"  latest="now">
        <![CDATA[index=cassandra_cache | dedup HOSTADDR|table HOSTADDR]]>
      </populatingSearch>
    </input> 
  </fieldset>
  
  
  <row>
    <table>
      <title>CPU Performance by Process Category</title>
      <searchString>index="cassandra_cpu" HOSTADDR=$node$| rename HOSTADDR AS server_name
        | transaction max(tstamp) by server_name [ search min(idle) | sort -idle | head 1 ]
        | stats max(tstamp) AS LATEST_TIME, min(idle) AS IDLE%, avg(user) AS USER_PROCESS%, avg(system) AS SYSTEM_PROCESS% by server_name</searchString>
      
      <latestTime>now</latestTime>
    </table>
  </row>
  <row>
    <chart>
      <title>CPU Idle Percentage over time</title>
      <searchString>index="cassandra_cpu" HOSTADDR=$node$ | rename HOSTADDR AS Server | timechart span=2m values(idle) AS Idle% by Server</searchString>
      
      <latestTime>now</latestTime>
      <option name="charting.axisTitleX.visibility">visible</option>
      <option name="charting.axisTitleY.visibility">visible</option>
      <option name="charting.axisX.scale">linear</option>
      <option name="charting.axisY.maximumNumber">100</option>
      <option name="charting.axisY.scale">linear</option>
      <option name="charting.chart">line</option>
      <option name="charting.chart.nullValueMode">gaps</option>
      <option name="charting.chart.sliceCollapsingThreshold">0.01</option>
      <option name="charting.chart.stackMode">default</option>
      <option name="charting.chart.style">shiny</option>
      <option name="charting.drilldown">all</option>
      <option name="charting.layout.splitSeries">0</option>
      <option name="charting.legend.labelStyle.overflowMode">ellipsisMiddle</option>
      <option name="charting.legend.placement">right</option>
      <option name="charting.axisTitleX.text">Time</option>
      <option name="charting.axisTitleY.text">Percentage</option>
    </chart>
    <chart>
      <title>IO Wait Percentage over time</title>
      <searchString>index="cassandra_cpu" HOSTADDR=$node$ | rename HOSTADDR AS Server | timechart span=2m values(iowait) AS Idle% by Server</searchString>
      
      <latestTime>now</latestTime>
      <option name="charting.axisTitleX.visibility">visible</option>
      <option name="charting.axisTitleY.visibility">visible</option>
      <option name="charting.axisX.scale">linear</option>
      <option name="charting.axisY.maximumNumber">100</option>
      <option name="charting.axisY.scale">linear</option>
      <option name="charting.chart">line</option>
      <option name="charting.chart.nullValueMode">gaps</option>
      <option name="charting.chart.sliceCollapsingThreshold">0.01</option>
      <option name="charting.chart.stackMode">default</option>
      <option name="charting.chart.style">shiny</option>
      <option name="charting.drilldown">all</option>
      <option name="charting.layout.splitSeries">0</option>
      <option name="charting.legend.labelStyle.overflowMode">ellipsisMiddle</option>
      <option name="charting.legend.placement">right</option>
      <option name="charting.axisTitleX.text">Time</option>
      <option name="charting.axisTitleY.text">Percentage</option>
    </chart>
  </row>
</form>