<nav search_view="search" color="#65A637">
  <view name="search" default='true' /> 
  <view name="data_models" />
<collection label="Dashboard Alarms">
  		<a href="/app/ossim/alarms/">Alarms</a>
  		<a href="/app/ossim/experimental/">Experimental</a>
  		<a href="/app/ossim/logger_intelligence/">Logger Intelligence</a>
</collection>
<collection label="Intelligent Alarms">
        <a href="/app/ossim/intelligent_alarm">DashBoard</a>
        <a href="/dj/ossim/parallel/">Promisc Host Parallel Sets</a>
  		<a href="/dj/ossim/sankey/">Promisc Host Last 24 Hrs</a>
</collection>
<collection label="Ossim System">
  		<a href="/app/ossim/Ossim_System/">DashBoard</a>
  		<a href="/app/ossim/ossim_errors/">Errors Inside OSSIM</a>
        <a href="/app/ossim/ossim_warning/">Warnings Inside OSSIM</a>
  		<a href="/app/ossim/ossim_system_events/">Trends</a>
</collection>  
  <view name="About" />
</nav>