<form>
  <label>LDAP user dynamic drop down</label>
  <description></description>
  <fieldset submitButton="false">
    <input type="dropdown" token="dn_tok" searchWhenChanged="true">
      <label>Select LDAP user:</label>
      <choice value="*">all</choice>
      <search>
        <query>| ldap | dedup cn | table cn dn</query>
        <earliest>$earliest$</earliest>
        <latest>$latest$</latest>
      </search>
      <prefix>cn=</prefix>
      <fieldForLabel>cn</fieldForLabel>
      <fieldForValue>cn</fieldForValue>
    </input>
  </fieldset>
  <row>
    <panel>
      <table>
        <title>LDAP Attributes</title>
        <search>
          <query>| ldap --filter="($dn_tok$)"</query>
          <earliest>-15m</earliest>
          <latest>now</latest>
        </search>
        <option name="count">10</option>
        <option name="dataOverlayMode">none</option>
        <option name="drilldown">cell</option>
        <option name="refresh.display">progressbar</option>
        <option name="rowNumbers">false</option>
        <option name="wrap">true</option>
      </table>
    </panel>
  </row>
</form>